Metadata-Version: 1.0
Name: py42hulk
Version: 0.1
Summary: The answer to everything!
Home-page: https://gitlab.com/theonov13/py42/
Author: Sebastian Schwalbe
Author-email: thenov13@gmail.com
License: APACHE2.0
Platform: UNKNOWN
